bandit_client/__init__.py
bandit_client/_compat.py
bandit_client/client.py
bandit_client-0.2.0.dist-info/METADATA
bandit_client-0.2.0.dist-info/RECORD
bandit_client-0.2.0.dist-info/WHEEL
bandit_client-0.2.0.dist-info/top_level.txt
