Metadata-Version: 2.1
Name: bandit-client
Version: 0.2.0
Summary: bandit client
Home-page: https://github.com/xiachufang/bandit-client
Author: Yana, GUOQIANG LIN
Author-email: yangyang@xiachufang.com, linguoqiang@xiachufang.com
License: MIT License
Keywords: bandit client
Platform: any
Requires-Dist: simplejson
Requires-Dist: requests
Requires-Dist: six
